README.rst
setup.py
edgeping/__init__.py
edgeping/server.py
edgeping.egg-info/PKG-INFO
edgeping.egg-info/SOURCES.txt
edgeping.egg-info/dependency_links.txt
edgeping.egg-info/entry_points.txt
edgeping.egg-info/not-zip-safe
edgeping.egg-info/top_level.txt