Metadata-Version: 1.1
Name: edgeping
Version: 0.1
Summary: Mozilla Edge Server.
Home-page: https://github.com/tarekziade/edgeping
Author: Tarek Ziade
Author-email: tarek@ziade.org
License: UNKNOWN
Platform: UNKNOWN
Classifier: Programming Language :: Python
Classifier: License :: OSI Approved :: Apache Software License
Classifier: Development Status :: 5 - Production/Stable
Classifier: Programming Language :: Python :: 3 :: Only
